[
    {
        "transactionName": "home_page",
        "rawStartTime": 1702146729644,
        "rawEndTime": 1702146730073
    },
    {
        "transactionName": "login",
        "rawStartTime": 1702146730147,
        "rawEndTime": 1702146730569
    },
    {
        "transactionName": "flights_page",
        "rawStartTime": 1702146730661,
        "rawEndTime": 1702146731102
    },
    {
        "transactionName": "search_flight",
        "rawStartTime": 1702146731177,
        "rawEndTime": 1702146731549
    },
    {
        "transactionName": "choose_ticket",
        "rawStartTime": 1702146731623,
        "rawEndTime": 1702146731994
    },
    {
        "transactionName": "payment_details",
        "rawStartTime": 1702146732070,
        "rawEndTime": 1702146732445
    },
    {
        "transactionName": "itinerary",
        "rawStartTime": 1702146732520,
        "rawEndTime": 1702146732967
    },
    {
        "transactionName": "UC1_BuyTicket",
        "rawStartTime": 1702146729589,
        "rawEndTime": 1702146733039
    }
]