[
    {
        "transactionName": "home_page",
        "rawStartTime": 1702147315729,
        "rawEndTime": 1702147316810
    },
    {
        "transactionName": "login",
        "rawStartTime": 1702147316881,
        "rawEndTime": 1702147317971
    },
    {
        "transactionName": "flights_page",
        "rawStartTime": 1702147318051,
        "rawEndTime": 1702147319163
    },
    {
        "transactionName": "search_flight",
        "rawStartTime": 1702147319240,
        "rawEndTime": 1702147320273
    },
    {
        "transactionName": "choose_ticket",
        "rawStartTime": 1702147320332,
        "rawEndTime": 1702147321372
    },
    {
        "transactionName": "payment_details",
        "rawStartTime": 1702147321451,
        "rawEndTime": 1702147322498
    },
    {
        "transactionName": "itinerary",
        "rawStartTime": 1702147322574,
        "rawEndTime": 1702147323686
    },
    {
        "transactionName": "UC1_BuyTicket",
        "rawStartTime": 1702147315659,
        "rawEndTime": 1702147323761
    }
]