[
    {
        "transactionName": "home_page",
        "rawStartTime": 1702146973702,
        "rawEndTime": 1702146974419
    },
    {
        "transactionName": "login",
        "rawStartTime": 1702146974505,
        "rawEndTime": 1702146975232
    },
    {
        "transactionName": "flights_page",
        "rawStartTime": 1702146975305,
        "rawEndTime": 1702146976047
    },
    {
        "transactionName": "search_flight",
        "rawStartTime": 1702146976119,
        "rawEndTime": 1702146976790
    },
    {
        "transactionName": "choose_ticket",
        "rawStartTime": 1702146976866,
        "rawEndTime": 1702146977531
    },
    {
        "transactionName": "payment_details",
        "rawStartTime": 1702146977612,
        "rawEndTime": 1702146978276
    },
    {
        "transactionName": "itinerary",
        "rawStartTime": 1702146978358,
        "rawEndTime": 1702146979106
    },
    {
        "transactionName": "UC1_BuyTicket",
        "rawStartTime": 1702146973640,
        "rawEndTime": 1702146979184
    }
]