[
    {
        "stepId": "STEP1821",
        "stepName": "Url: welcome.pl",
        "infFile": "t1.inf",
        "time": 1702147883060
    },
    {
        "stepId": "STEP1822",
        "stepName": "Submit Data: login.pl",
        "infFile": "t2.inf",
        "time": 1702147884754
    },
    {
        "stepId": "STEP1823",
        "stepName": "Url: Search Flights Button",
        "infFile": "t3.inf",
        "time": 1702147886447
    },
    {
        "stepId": "STEP1824",
        "stepName": "Submit Data: reservations.pl",
        "infFile": "t4.inf",
        "time": 1702147888095
    },
    {
        "stepId": "STEP1825",
        "stepName": "Submit Data: reservations.pl_2",
        "infFile": "t5.inf",
        "time": 1702147889741
    },
    {
        "stepId": "STEP1826",
        "stepName": "Submit Data: reservations.pl_3",
        "infFile": "t6.inf",
        "time": 1702147891380
    },
    {
        "stepId": "STEP1827",
        "stepName": "Url: Itinerary Button",
        "infFile": "t7.inf",
        "time": 1702147893099
    }
]