[
    {
        "transactionName": "home_page",
        "rawStartTime": 1702148400321,
        "rawEndTime": 1702148402385
    },
    {
        "transactionName": "login",
        "rawStartTime": 1702148402462,
        "rawEndTime": 1702148404537
    },
    {
        "transactionName": "flights_page",
        "rawStartTime": 1702148404615,
        "rawEndTime": 1702148406733
    },
    {
        "transactionName": "search_flight",
        "rawStartTime": 1702148406806,
        "rawEndTime": 1702148408810
    },
    {
        "transactionName": "choose_ticket",
        "rawStartTime": 1702148408883,
        "rawEndTime": 1702148410898
    },
    {
        "transactionName": "payment_details",
        "rawStartTime": 1702148410974,
        "rawEndTime": 1702148412963
    },
    {
        "transactionName": "itinerary",
        "rawStartTime": 1702148413035,
        "rawEndTime": 1702148415114
    },
    {
        "transactionName": "UC1_BuyTicket",
        "rawStartTime": 1702148400238,
        "rawEndTime": 1702148415189
    }
]